<?xml version="1.0" encoding="utf-8" ?>
<dwsync>
<file name="summernote.min.js" server="litegroup.com.br/www/tccifsp/" local="132556284760000000" remote="132556284760000000" Dst="0" />
<file name="summernote-bs4.css" server="litegroup.com.br/www/tccifsp/" local="132556284240000000" remote="132556284240000000" Dst="0" />
<file name="summernote-bs4.min.js" server="litegroup.com.br/www/tccifsp/" local="132556284410000000" remote="132556284410000000" Dst="0" />
<file name="summernote-bs4.min.js.map" server="litegroup.com.br/www/tccifsp/" local="132556284460000000" remote="132556284460000000" Dst="0" />
<file name="summernote-lite.js.map" server="litegroup.com.br/www/tccifsp/" local="132556284530000000" remote="132556284530000000" Dst="0" />
<file name="summernote-lite.min.js.LICENSE.txt" server="litegroup.com.br/www/tccifsp/" local="132556284570000000" remote="132556284570000000" Dst="0" />
<file name="summernote.min.css" server="litegroup.com.br/www/tccifsp/" local="132556284750000000" remote="132556284750000000" Dst="0" />
<file name="summernote.min.js.map" server="litegroup.com.br/www/tccifsp/" local="132556284810000000" remote="132556284810000000" Dst="0" />
<file name="summernote.js" server="litegroup.com.br/www/tccifsp/" local="132556284700000000" remote="132556284700000000" Dst="0" />
<file name="summernote-lite.min.css" server="litegroup.com.br/www/tccifsp/" local="132556284540000000" remote="132556284540000000" Dst="0" />
<file name="summernote-bs4.js.map" server="litegroup.com.br/www/tccifsp/" local="132556284400000000" remote="132556284400000000" Dst="0" />
<file name="summernote-bs4.min.css" server="litegroup.com.br/www/tccifsp/" local="132556284400000000" remote="132556284400000000" Dst="0" />
<file name="summernote-lite.js" server="litegroup.com.br/www/tccifsp/" local="132556284490000000" remote="132556284490000000" Dst="0" />
<file name="summernote-lite.min.js" server="litegroup.com.br/www/tccifsp/" local="132556284570000000" remote="132556284570000000" Dst="0" />
<file name="summernote.js.map" server="litegroup.com.br/www/tccifsp/" local="132556284750000000" remote="132556284750000000" Dst="0" />
<file name="summernote-bs4.min.js.LICENSE.txt" server="litegroup.com.br/www/tccifsp/" local="132556284410000000" remote="132556284410000000" Dst="0" />
<file name="summernote-bs4.js" server="litegroup.com.br/www/tccifsp/" local="132556284290000000" remote="132556284290000000" Dst="0" />
<file name="summernote-lite.min.js.map" server="litegroup.com.br/www/tccifsp/" local="132556284600000000" remote="132556284600000000" Dst="0" />
<file name="summernote-lite.css" server="litegroup.com.br/www/tccifsp/" local="132556284470000000" remote="132556284470000000" Dst="0" />
<file name="summernote.min.js.LICENSE.txt" server="litegroup.com.br/www/tccifsp/" local="132556284760000000" remote="132556284760000000" Dst="0" />
<file name="summernote.css" server="litegroup.com.br/www/tccifsp/" local="132556284610000000" remote="132556284610000000" Dst="0" />
</dwsync>